leopardi/__init__.py
leopardi/_blender.py
leopardi/backgrounds.py
leopardi/camera.py
leopardi/leopardi.py
leopardi/lighting.py
leopardi/models.py
leopardi/renderer.py
leopardi-0.2.24.dist-info/LICENSE
leopardi-0.2.24.dist-info/METADATA
leopardi-0.2.24.dist-info/WHEEL
leopardi-0.2.24.dist-info/top_level.txt
leopardi-0.2.24.dist-info/RECORD
