Metadata-Version: 2.1
Name: leopardi
Version: 0.2.24
Summary: An extensible library for generating 3D synthetic data with Blender that just works.
Home-page: https://github.com/johnsutor/leopardi
Author: John Sutor
Author-email: johnsutor3@gmail.com
License: UNKNOWN
Project-URL: Homepage, https://github.com/johnsutor/leopardi
Keywords: synthetic data blender 3d machine learning rendering images yolo coco pascal voc
Platform: UNKNOWN
Classifier: Programming Language :: Python :: 3
Classifier: Development Status :: 2 - Pre-Alpha
Classifier: License :: OSI Approved :: GNU General Public License v3 (GPLv3)
Classifier: Operating System :: OS Independent
Requires-Python: >=3.5
Requires-Dist: joblib
Requires-Dist: Pillow
